{
  "id": "palindromos",
  "title": "pálinDrómos",
  "slug": "palindromos",
  "category": "experiment",
  "categoryLabel": "Expérimentation",
  "shortDescription": "Vérificateur de palindrome interactif, réalisé dans le cadre de la certification freeCodeCamp.",
  "technologies": ["JavaScript", "HTML", "CSS"],
  "skills": ["Basiques de JavaScript", "Manipulation du DOM"],
  "featured": false,
  "priority": 11,
  "images": {
    "thumbnail": "/img/projects/palindromos/palindromos-thumbnail.jpg",
    "hero": "/img/projects/palindromos/palindromos-thumbnail.jpg"
  },
  "links": {
    "live": "https://palindromos.sandbox.leopeyronnet.fr/",
    "github": "https://github.com/LaiPe/palindromos"
  },
  "client": null,
  "date": "Octobre 2024",
  "duration": "1 semaine"
}
